image_proceosimoes_image_processor-0.1.0.dist-info/licenses/LICENSE
image_processor/__init__.py
image_processor/filters.py
image_processor/transformations.py
image_processor/utils.py
tests/__init__.py
tests/test_filters.py
image_proceosimoes_image_processor-0.1.0.dist-info/METADATA
image_proceosimoes_image_processor-0.1.0.dist-info/WHEEL
image_proceosimoes_image_processor-0.1.0.dist-info/top_level.txt
image_proceosimoes_image_processor-0.1.0.dist-info/RECORD
